itential/__init__.py
itential/core.py
itential/modules/__init__.py
itential/modules/utils.py
itential/modules/v2020_2/__init__.py
itential/modules/v2020_2/_adapter_automation_gateway.py
itential/modules/v2020_2/_app_admin_essentials.py
itential/modules/v2020_2/_app_ag_manager.py
itential/modules/v2020_2/_app_automation_catalog.py
itential/modules/v2020_2/_app_automation_studio.py
itential/modules/v2020_2/_app_configuration_manager.py
itential/modules/v2020_2/_app_form_builder.py
itential/modules/v2020_2/_app_json_forms.py
itential/modules/v2020_2/_app_jst.py
itential/modules/v2020_2/_app_mop.py
itential/modules/v2020_2/_app_nso_manager.py
itential/modules/v2020_2/_app_operations_manager.py
itential/modules/v2020_2/_app_service_catalog.py
itential/modules/v2020_2/_app_service_management.py
itential/modules/v2020_2/_app_task_worker.py
itential/modules/v2020_2/_app_template_builder.py
itential/modules/v2020_2/_app_workflow_builder.py
itential/modules/v2020_2/_app_workflow_engine.py
itential/modules/v2020_2/_pronghorn_core.py
itential/modules/v2021_1/__init__.py
itential/modules/v2021_1/_app_form_builder.py
itential/modules/v2021_1/_app_workflow_builder.py
itential/modules/v2021_2/__init__.py
itential/modules/v2021_2/_app_form_builder.py
itential.py-1.0.0.dist-info/LICENSE
itential.py-1.0.0.dist-info/METADATA
itential.py-1.0.0.dist-info/WHEEL
itential.py-1.0.0.dist-info/top_level.txt
itential.py-1.0.0.dist-info/RECORD
