Metadata-Version: 2.1
Name: itential.py
Version: 1.0.0
Summary: A Python wrapper for the Itential API.
Author: Tagmeh
License: The MIT License (MIT)
Project-URL: Homepage, https://github.com/tagmeh/Itential.py
Project-URL: Bug Tracker, https://github.com/tagmeh/Itential.py/issues
Classifier: Programming Language :: Python :: 3
Classifier: Programming Language :: Python :: 3.8
Classifier: License :: OSI Approved :: MIT License
Classifier: Operating System :: OS Independent
Classifier: Natural Language :: English
Classifier: Topic :: Software Development :: Libraries
Classifier: Topic :: Software Development :: Libraries :: Python Modules
Classifier: Topic :: Utilities
Classifier: Typing :: Typed
Requires-Python: >=3.8
License-File: LICENSE
Requires-Dist: requests (~=2.28)
